Metadata-Version: 1.1
Name: scikit-stack
Version: 3.0
Summary: skstack for combining pattern classifiers
Home-page: http://github.com/ivallesp/stacker
Author: Ivan Valles Perez
Author-email: ivanvallesperez@gmail.com
License: UNKNOWN
Download-URL: https://github.com/ivallesp/scikit-stack/tarball/V3
Platform: UNKNOWN
